rich_format/__init__.py
rich_format/app.py
rich_format/test.py
rich_format-0.0.4.dist-info/LICENSE
rich_format-0.0.4.dist-info/METADATA
rich_format-0.0.4.dist-info/WHEEL
rich_format-0.0.4.dist-info/entry_points.txt
rich_format-0.0.4.dist-info/top_level.txt
rich_format-0.0.4.dist-info/zip-safe
rich_format-0.0.4.dist-info/RECORD
