Metadata-Version: 2.1
Name: rich-format
Version: 0.0.4
Summary: Format rich Text
Home-page: https://github.com/pom11/rich_format
Author: pom11
Author-email: office@parsecom.ro
License: MIT license
Keywords: rich
Classifier: Development Status :: 5 - Production/Stable
Classifier: Intended Audience :: Developers
Classifier: License :: OSI Approved :: MIT License
Classifier: Natural Language :: English
Classifier: Programming Language :: Python :: 3.6
Classifier: Programming Language :: Python :: 3.7
Classifier: Programming Language :: Python :: 3.8
Classifier: Programming Language :: Python :: 3.9
Classifier: Programming Language :: Python :: 3.10
Classifier: Programming Language :: Python :: 3.11
Requires-Python: >=3.6
License-File: LICENSE
Requires-Dist: rich
Requires-Dist: textual
